dock2sing/__init__.py
dock2sing/docker_to_singularity.py
dock2sing/singularity_compose_validator.py
dock2sing-1.0.0.dist-info/LICENSE
dock2sing-1.0.0.dist-info/METADATA
dock2sing-1.0.0.dist-info/WHEEL
dock2sing-1.0.0.dist-info/entry_points.txt
dock2sing-1.0.0.dist-info/RECORD
