Metadata-Version: 2.3
Name: dock2sing
Version: 1.0.0
Summary: A Python-based tool for converting Docker Compose configurations to Singularity Compose format
Author: Adam Labadorf
Author-email: alabadorf@gmail.com
Requires-Python: >=3.12,<4.0
Classifier: Programming Language :: Python :: 3
Classifier: Programming Language :: Python :: 3.12
Classifier: Programming Language :: Python :: 3.13
Requires-Dist: colorama (>=0.4.6,<0.5.0)
Requires-Dist: pyyaml (>=6.0.2,<7.0.0)
